pysrag/__init__.py
pysrag/data/__init__.py
pysrag/data/_epiweek.py
pysrag/data/_srag.py
pysrag/data/common_data.csv
pysrag/model/__init__.py
pysrag/model/_gbm_trainer.py
pysrag/model/_lognormal_estimator.py
PySRAG-0.2.1.dist-info/LICENSE
PySRAG-0.2.1.dist-info/METADATA
PySRAG-0.2.1.dist-info/WHEEL
PySRAG-0.2.1.dist-info/top_level.txt
PySRAG-0.2.1.dist-info/RECORD
