Metadata-Version: 2.2
Name: PySRAG
Version: 0.2.1
Summary: This Python package provides tools for analyzing and processing data related to Severe Acute Respiratory Syndrome (SARS) and other respiratory viruses. It includes functions for data preprocessing, feature engineering, and training Gradient Boosting Models (GBMs) for binary or multiclass classification.
Home-page: https://github.com/joao-1988/PySRAG
Author: João Flávio Andrade Silva
Author-email: joaoflavio1988@gmail.com
License: MIT
Classifier: License :: OSI Approved :: MIT License
Classifier: Programming Language :: Python :: 3
Classifier: Operating System :: OS Independent
License-File: LICENSE
Requires-Dist: numpy
Requires-Dist: pandas
Requires-Dist: scikit-learn
Requires-Dist: lightgbm
Requires-Dist: datetime
Dynamic: author
Dynamic: author-email
Dynamic: classifier
Dynamic: description
Dynamic: description-content-type
Dynamic: home-page
Dynamic: license
Dynamic: requires-dist
Dynamic: summary
